fiskalhr/__init__.py
fiskalhr/enums.py
fiskalhr/errors.py
fiskalhr/invoice.py
fiskalhr/item.py
fiskalhr/meta.py
fiskalhr/oib.py
fiskalhr/signature.py
fiskalhr/utils.py
fiskalhr/ws.py
fiskalhr/zki.py
fiskal_hr-0.9.1.dist-info/LICENSE
fiskal_hr-0.9.1.dist-info/METADATA
fiskal_hr-0.9.1.dist-info/WHEEL
fiskal_hr-0.9.1.dist-info/top_level.txt
fiskal_hr-0.9.1.dist-info/RECORD
