Metadata-Version: 2.1
Name: fiskal-hr
Version: 0.9.1
Summary: Client for Croatian Fiskalizacija tax service
Author-email: Senko Rasic <senko@senko.net>
License: MIT
Project-URL: Homepage, https://github.com/senko/fiskal-hr/
Project-URL: Bug Tracker, https://github.com/senko/fiskal-hr/issues
Keywords: fiskalizacija
Classifier: Programming Language :: Python :: 3
Requires-Python: >=3.6
License-File: LICENSE
Requires-Dist: cryptography
Requires-Dist: xmlsec
Requires-Dist: zeep
